Metadata-Version: 2.1
Name: glogger
Version: 1.1.0
Summary: A python library for logging loguru messages straight to a gelf instance, for example Sematext via HTTP
Home-page: https://github.com/fino-digital/glogger
License: UNKNOWN
Platform: UNKNOWN
Classifier: Programming Language :: Python :: 3.7
Classifier: License :: OSI Approved :: MIT License
Classifier: Operating System :: OS Independent
Requires-Python: >=3.6
